kryten_moderator/__init__.py
kryten_moderator/__main__.py
kryten_moderator/ip_manager.py
kryten_moderator/metrics_server.py
kryten_moderator/moderation_list.py
kryten_moderator/nats_handler.py
kryten_moderator/pattern_manager.py
kryten_moderator/service.py
kryten_moderator-0.4.0.dist-info/METADATA
kryten_moderator-0.4.0.dist-info/WHEEL
kryten_moderator-0.4.0.dist-info/entry_points.txt
kryten_moderator-0.4.0.dist-info/licenses/LICENSE
kryten_moderator-0.4.0.dist-info/RECORD
