Metadata-Version: 2.4
Name: kryten-moderator
Version: 0.4.0
Summary: Kryten moderation service - handles chat moderation and filtering
Project-URL: Homepage, https://github.com/grobertson/kryten-moderator
Project-URL: Repository, https://github.com/grobertson/kryten-moderator
Project-URL: Issues, https://github.com/grobertson/kryten-moderator/issues
Author-email: Kryten Robot Team <geoff@beaverdog.io>
License: MIT
License-File: LICENSE
Keywords: chat,cytube,microservices,moderation,nats
Classifier: Development Status :: 3 - Alpha
Classifier: Intended Audience :: Developers
Classifier: License :: OSI Approved :: MIT License
Classifier: Programming Language :: Python :: 3
Classifier: Programming Language :: Python :: 3.10
Classifier: Programming Language :: Python :: 3.11
Classifier: Programming Language :: Python :: 3.12
Classifier: Topic :: Communications :: Chat
Classifier: Topic :: Software Development :: Libraries :: Python Modules
Requires-Python: >=3.10
Requires-Dist: kryten-py>=0.9.11
